{
	"info": {
		"_postman_id": "48c6b3c0-e81c-4c85-be37-885866c5b9c8",
		"name": "Pendrive Loan Tracking System",
		"schema": "https://schema.getpostman.com/json/collection/v2.1.0/collection.json",
		"_exporter_id": "16632302"
	},
	"item": [
		{
			"name": "Demand",
			"item": [
				{
					"name": "Get All Demand",
					"event": [
						{
							"listen": "test",
							"script": {
								"exec": [
									"pm.test(\"Status code is 200\", function () {",
									"    pm.response.to.have.status(200);",
									"});"
								],
								"type": "text/javascript"
							}
						}
					],
					"request": {
						"method": "GET",
						"header": [],
						"url": {
							"raw": "{{base_url}}/api/demands",
							"host": [
								"{{base_url}}"
							],
							"path": [
								"api",
								"demands"
							]
						},
						"description": "This is a GET request and it is used to \"get\" data from an endpoint. There is no request body for a GET request, but you can use query parameters to help specify the resource you want data on (e.g., in this request, we have `id=1`).\n\nA successful GET response will have a `200 OK` status, and should include some kind of response body - for example, HTML web content or JSON data."
					},
					"response": []
				},
				{
					"name": "Get Demand by Id",
					"event": [
						{
							"listen": "test",
							"script": {
								"exec": [
									"pm.test(\"Status code is 200\", function () {",
									"    pm.response.to.have.status(200);",
									"});"
								],
								"type": "text/javascript"
							}
						}
					],
					"request": {
						"method": "GET",
						"header": [],
						"url": {
							"raw": "{{base_url}}/api/demands/DMND0000001",
							"host": [
								"{{base_url}}"
							],
							"path": [
								"api",
								"demands",
								"DMND0000001"
							]
						},
						"description": "This is a GET request and it is used to \"get\" data from an endpoint. There is no request body for a GET request, but you can use query parameters to help specify the resource you want data on (e.g., in this request, we have `id=1`).\n\nA successful GET response will have a `200 OK` status, and should include some kind of response body - for example, HTML web content or JSON data."
					},
					"response": []
				},
				{
					"name": "Post Demand",
					"event": [
						{
							"listen": "test",
							"script": {
								"exec": [
									"pm.test(\"Successful POST request\", function () {",
									"    pm.expect(pm.response.code).to.be.oneOf([200, 201]);",
									"});",
									""
								],
								"type": "text/javascript"
							}
						}
					],
					"request": {
						"method": "POST",
						"header": [],
						"body": {
							"mode": "raw",
							"raw": "{\n    \"name\": \"Demand 4\"\n}",
							"options": {
								"raw": {
									"language": "json"
								}
							}
						},
						"url": {
							"raw": "{{base_url}}/api/demands",
							"host": [
								"{{base_url}}"
							],
							"path": [
								"api",
								"demands"
							]
						},
						"description": "This is a POST request, submitting data to an API via the request body. This request submits JSON data, and the data is reflected in the response.\n\nA successful POST request typically returns a `200 OK` or `201 Created` response code."
					},
					"response": []
				},
				{
					"name": "Update Demand by Id",
					"event": [
						{
							"listen": "test",
							"script": {
								"exec": [
									"pm.test(\"Successful PUT request\", function () {",
									"    pm.expect(pm.response.code).to.be.oneOf([200, 201, 204]);",
									"});",
									""
								],
								"type": "text/javascript"
							}
						}
					],
					"request": {
						"method": "PUT",
						"header": [],
						"body": {
							"mode": "raw",
							"raw": "{\n    \"name\": \"Demand 1 New\"\n}",
							"options": {
								"raw": {
									"language": "json"
								}
							}
						},
						"url": {
							"raw": "{{base_url}}/api/demands/DMND0000001",
							"host": [
								"{{base_url}}"
							],
							"path": [
								"api",
								"demands",
								"DMND0000001"
							]
						},
						"description": "This is a PUT request and it is used to overwrite an existing piece of data. For instance, after you create an entity with a POST request, you may want to modify that later. You can do that using a PUT request. You typically identify the entity being updated by including an identifier in the URL (eg. `id=1`).\n\nA successful PUT request typically returns a `200 OK`, `201 Created`, or `204 No Content` response code."
					},
					"response": []
				},
				{
					"name": "Delete All Demands",
					"event": [
						{
							"listen": "test",
							"script": {
								"exec": [
									"pm.test(\"Successful DELETE request\", function () {",
									"    pm.expect(pm.response.code).to.be.oneOf([200, 202, 204]);",
									"});",
									""
								],
								"type": "text/javascript"
							}
						}
					],
					"request": {
						"method": "DELETE",
						"header": [],
						"body": {
							"mode": "raw",
							"raw": "",
							"options": {
								"raw": {
									"language": "json"
								}
							}
						},
						"url": {
							"raw": "{{base_url}}/api/demands",
							"host": [
								"{{base_url}}"
							],
							"path": [
								"api",
								"demands"
							]
						},
						"description": "This is a DELETE request, and it is used to delete data that was previously created via a POST request. You typically identify the entity being updated by including an identifier in the URL (eg. `id=1`).\n\nA successful DELETE request typically returns a `200 OK`, `202 Accepted`, or `204 No Content` response code."
					},
					"response": []
				},
				{
					"name": "Delete Demand by Id",
					"event": [
						{
							"listen": "test",
							"script": {
								"exec": [
									"pm.test(\"Successful DELETE request\", function () {",
									"    pm.expect(pm.response.code).to.be.oneOf([200, 202, 204]);",
									"});",
									""
								],
								"type": "text/javascript"
							}
						}
					],
					"request": {
						"method": "DELETE",
						"header": [],
						"body": {
							"mode": "raw",
							"raw": "",
							"options": {
								"raw": {
									"language": "json"
								}
							}
						},
						"url": {
							"raw": "{{base_url}}/api/demands/DMND0000002",
							"host": [
								"{{base_url}}"
							],
							"path": [
								"api",
								"demands",
								"DMND0000002"
							]
						},
						"description": "This is a DELETE request, and it is used to delete data that was previously created via a POST request. You typically identify the entity being updated by including an identifier in the URL (eg. `id=1`).\n\nA successful DELETE request typically returns a `200 OK`, `202 Accepted`, or `204 No Content` response code."
					},
					"response": []
				}
			]
		},
		{
			"name": "Loan Request",
			"item": [
				{
					"name": "Get All Loan Request",
					"event": [
						{
							"listen": "test",
							"script": {
								"exec": [
									"pm.test(\"Status code is 200\", function () {",
									"    pm.response.to.have.status(200);",
									"});"
								],
								"type": "text/javascript"
							}
						}
					],
					"request": {
						"method": "GET",
						"header": [],
						"url": {
							"raw": "{{base_url}}/api/loanRequests",
							"host": [
								"{{base_url}}"
							],
							"path": [
								"api",
								"loanRequests"
							]
						},
						"description": "This is a GET request and it is used to \"get\" data from an endpoint. There is no request body for a GET request, but you can use query parameters to help specify the resource you want data on (e.g., in this request, we have `id=1`).\n\nA successful GET response will have a `200 OK` status, and should include some kind of response body - for example, HTML web content or JSON data."
					},
					"response": []
				},
				{
					"name": "Get Loan Request by Id",
					"event": [
						{
							"listen": "test",
							"script": {
								"exec": [
									"pm.test(\"Status code is 200\", function () {",
									"    pm.response.to.have.status(200);",
									"});"
								],
								"type": "text/javascript"
							}
						}
					],
					"request": {
						"method": "GET",
						"header": [],
						"url": {
							"raw": "{{base_url}}/api/loanRequests/PRRQ0000001",
							"host": [
								"{{base_url}}"
							],
							"path": [
								"api",
								"loanRequests",
								"PRRQ0000001"
							]
						},
						"description": "This is a GET request and it is used to \"get\" data from an endpoint. There is no request body for a GET request, but you can use query parameters to help specify the resource you want data on (e.g., in this request, we have `id=1`).\n\nA successful GET response will have a `200 OK` status, and should include some kind of response body - for example, HTML web content or JSON data."
					},
					"response": []
				},
				{
					"name": "Post Loan Request",
					"event": [
						{
							"listen": "test",
							"script": {
								"exec": [
									"pm.test(\"Successful POST request\", function () {",
									"    pm.expect(pm.response.code).to.be.oneOf([200, 201]);",
									"});",
									""
								],
								"type": "text/javascript"
							}
						}
					],
					"request": {
						"method": "POST",
						"header": [],
						"body": {
							"mode": "raw",
							"raw": "{\n    \"name\": \"Request 1\",\n    \"startDate\": \"2024-03-15\",\n    \"endDate\": \"2024-03-10\",\n    \"demandId\": \"DMND0000004\",\n    \"createdById\": \"f489fdb3-24c4-413d-a04a-8ab3c1b1e415\",\n    \"pendriveIds\": [\n        5, 6\n    ]\n}",
							"options": {
								"raw": {
									"language": "json"
								}
							}
						},
						"url": {
							"raw": "{{base_url}}/api/loanRequests",
							"host": [
								"{{base_url}}"
							],
							"path": [
								"api",
								"loanRequests"
							]
						},
						"description": "This is a POST request, submitting data to an API via the request body. This request submits JSON data, and the data is reflected in the response.\n\nA successful POST request typically returns a `200 OK` or `201 Created` response code."
					},
					"response": []
				},
				{
					"name": "Update Loan Request by Id",
					"event": [
						{
							"listen": "test",
							"script": {
								"exec": [
									"pm.test(\"Successful PUT request\", function () {",
									"    pm.expect(pm.response.code).to.be.oneOf([200, 201, 204]);",
									"});",
									""
								],
								"type": "text/javascript"
							}
						}
					],
					"request": {
						"method": "PUT",
						"header": [],
						"body": {
							"mode": "raw",
							"raw": "{\n    \"requestStatusId\": \"3\",\n    \"returnDate\": \"2024-03-12\",\n    \"approvedById\": \"ee1fde29-ce2c-4695-ab2c-83e6a6d6c26e\",\n    \"returnApprovedById\": \"ee1fde29-ce2c-4695-ab2c-83e6a6d6c26e\",\n    \"pendriveIds\": [\n        5,\n        7\n    ]\n}",
							"options": {
								"raw": {
									"language": "json"
								}
							}
						},
						"url": {
							"raw": "{{base_url}}/api/loanRequests/PRRQ0000001",
							"host": [
								"{{base_url}}"
							],
							"path": [
								"api",
								"loanRequests",
								"PRRQ0000001"
							]
						},
						"description": "This is a PUT request and it is used to overwrite an existing piece of data. For instance, after you create an entity with a POST request, you may want to modify that later. You can do that using a PUT request. You typically identify the entity being updated by including an identifier in the URL (eg. `id=1`).\n\nA successful PUT request typically returns a `200 OK`, `201 Created`, or `204 No Content` response code."
					},
					"response": []
				},
				{
					"name": "Delete All Loan Requests",
					"event": [
						{
							"listen": "test",
							"script": {
								"exec": [
									"pm.test(\"Successful DELETE request\", function () {",
									"    pm.expect(pm.response.code).to.be.oneOf([200, 202, 204]);",
									"});",
									""
								],
								"type": "text/javascript"
							}
						}
					],
					"request": {
						"method": "DELETE",
						"header": [],
						"body": {
							"mode": "raw",
							"raw": "",
							"options": {
								"raw": {
									"language": "json"
								}
							}
						},
						"url": {
							"raw": "{{base_url}}/api/loanRequests",
							"host": [
								"{{base_url}}"
							],
							"path": [
								"api",
								"loanRequests"
							]
						},
						"description": "This is a DELETE request, and it is used to delete data that was previously created via a POST request. You typically identify the entity being updated by including an identifier in the URL (eg. `id=1`).\n\nA successful DELETE request typically returns a `200 OK`, `202 Accepted`, or `204 No Content` response code."
					},
					"response": []
				},
				{
					"name": "Delete Loan Request by Id",
					"event": [
						{
							"listen": "test",
							"script": {
								"exec": [
									"pm.test(\"Successful DELETE request\", function () {",
									"    pm.expect(pm.response.code).to.be.oneOf([200, 202, 204]);",
									"});",
									""
								],
								"type": "text/javascript"
							}
						}
					],
					"request": {
						"method": "DELETE",
						"header": [],
						"body": {
							"mode": "raw",
							"raw": "",
							"options": {
								"raw": {
									"language": "json"
								}
							}
						},
						"url": {
							"raw": "{{base_url}}/api/loanRequests/PRRQ0000001",
							"host": [
								"{{base_url}}"
							],
							"path": [
								"api",
								"loanRequests",
								"PRRQ0000001"
							]
						},
						"description": "This is a DELETE request, and it is used to delete data that was previously created via a POST request. You typically identify the entity being updated by including an identifier in the URL (eg. `id=1`).\n\nA successful DELETE request typically returns a `200 OK`, `202 Accepted`, or `204 No Content` response code."
					},
					"response": []
				}
			]
		},
		{
			"name": "Loan Type",
			"item": [
				{
					"name": "Get All Loan Type",
					"event": [
						{
							"listen": "test",
							"script": {
								"exec": [
									"pm.test(\"Status code is 200\", function () {",
									"    pm.response.to.have.status(200);",
									"});"
								],
								"type": "text/javascript"
							}
						}
					],
					"request": {
						"method": "GET",
						"header": [],
						"url": {
							"raw": "{{base_url}}/api/loanTypes",
							"host": [
								"{{base_url}}"
							],
							"path": [
								"api",
								"loanTypes"
							]
						},
						"description": "This is a GET request and it is used to \"get\" data from an endpoint. There is no request body for a GET request, but you can use query parameters to help specify the resource you want data on (e.g., in this request, we have `id=1`).\n\nA successful GET response will have a `200 OK` status, and should include some kind of response body - for example, HTML web content or JSON data."
					},
					"response": []
				},
				{
					"name": "Get Loan Type by Id",
					"event": [
						{
							"listen": "test",
							"script": {
								"exec": [
									"pm.test(\"Status code is 200\", function () {",
									"    pm.response.to.have.status(200);",
									"});"
								],
								"type": "text/javascript"
							}
						}
					],
					"request": {
						"method": "GET",
						"header": [],
						"url": {
							"raw": "{{base_url}}/api/loanTypes/3",
							"host": [
								"{{base_url}}"
							],
							"path": [
								"api",
								"loanTypes",
								"3"
							]
						},
						"description": "This is a GET request and it is used to \"get\" data from an endpoint. There is no request body for a GET request, but you can use query parameters to help specify the resource you want data on (e.g., in this request, we have `id=1`).\n\nA successful GET response will have a `200 OK` status, and should include some kind of response body - for example, HTML web content or JSON data."
					},
					"response": []
				},
				{
					"name": "Post Loan Type",
					"event": [
						{
							"listen": "test",
							"script": {
								"exec": [
									"pm.test(\"Successful POST request\", function () {",
									"    pm.expect(pm.response.code).to.be.oneOf([200, 201]);",
									"});",
									""
								],
								"type": "text/javascript"
							}
						}
					],
					"request": {
						"method": "POST",
						"header": [],
						"body": {
							"mode": "raw",
							"raw": "{\n    \"description\": \"Personal_Loan\"\n}",
							"options": {
								"raw": {
									"language": "json"
								}
							}
						},
						"url": {
							"raw": "{{base_url}}/api/loanTypes",
							"host": [
								"{{base_url}}"
							],
							"path": [
								"api",
								"loanTypes"
							]
						},
						"description": "This is a POST request, submitting data to an API via the request body. This request submits JSON data, and the data is reflected in the response.\n\nA successful POST request typically returns a `200 OK` or `201 Created` response code."
					},
					"response": []
				},
				{
					"name": "Update Loan Type by Id",
					"event": [
						{
							"listen": "test",
							"script": {
								"exec": [
									"pm.test(\"Successful PUT request\", function () {",
									"    pm.expect(pm.response.code).to.be.oneOf([200, 201, 204]);",
									"});",
									""
								],
								"type": "text/javascript"
							}
						}
					],
					"request": {
						"method": "PUT",
						"header": [],
						"body": {
							"mode": "raw",
							"raw": "{\n    \"description\": \"Prepared\"\n}",
							"options": {
								"raw": {
									"language": "json"
								}
							}
						},
						"url": {
							"raw": "{{base_url}}/api/loanTypes/3",
							"host": [
								"{{base_url}}"
							],
							"path": [
								"api",
								"loanTypes",
								"3"
							]
						},
						"description": "This is a PUT request and it is used to overwrite an existing piece of data. For instance, after you create an entity with a POST request, you may want to modify that later. You can do that using a PUT request. You typically identify the entity being updated by including an identifier in the URL (eg. `id=1`).\n\nA successful PUT request typically returns a `200 OK`, `201 Created`, or `204 No Content` response code."
					},
					"response": []
				},
				{
					"name": "Delete All Loan Type",
					"event": [
						{
							"listen": "test",
							"script": {
								"exec": [
									"pm.test(\"Successful DELETE request\", function () {",
									"    pm.expect(pm.response.code).to.be.oneOf([200, 202, 204]);",
									"});",
									""
								],
								"type": "text/javascript"
							}
						}
					],
					"request": {
						"method": "DELETE",
						"header": [],
						"body": {
							"mode": "raw",
							"raw": "",
							"options": {
								"raw": {
									"language": "json"
								}
							}
						},
						"url": {
							"raw": "{{base_url}}/api/loanTypes",
							"host": [
								"{{base_url}}"
							],
							"path": [
								"api",
								"loanTypes"
							]
						},
						"description": "This is a DELETE request, and it is used to delete data that was previously created via a POST request. You typically identify the entity being updated by including an identifier in the URL (eg. `id=1`).\n\nA successful DELETE request typically returns a `200 OK`, `202 Accepted`, or `204 No Content` response code."
					},
					"response": []
				},
				{
					"name": "Delete Loan Type by Id",
					"event": [
						{
							"listen": "test",
							"script": {
								"exec": [
									"pm.test(\"Successful DELETE request\", function () {",
									"    pm.expect(pm.response.code).to.be.oneOf([200, 202, 204]);",
									"});",
									""
								],
								"type": "text/javascript"
							}
						}
					],
					"request": {
						"method": "DELETE",
						"header": [],
						"body": {
							"mode": "raw",
							"raw": "",
							"options": {
								"raw": {
									"language": "json"
								}
							}
						},
						"url": {
							"raw": "{{base_url}}/api/loanTypes/3",
							"host": [
								"{{base_url}}"
							],
							"path": [
								"api",
								"loanTypes",
								"3"
							]
						},
						"description": "This is a DELETE request, and it is used to delete data that was previously created via a POST request. You typically identify the entity being updated by including an identifier in the URL (eg. `id=1`).\n\nA successful DELETE request typically returns a `200 OK`, `202 Accepted`, or `204 No Content` response code."
					},
					"response": []
				}
			]
		},
		{
			"name": "Pendrive",
			"item": [
				{
					"name": "Get All Pendrive",
					"event": [
						{
							"listen": "test",
							"script": {
								"exec": [
									"pm.test(\"Status code is 200\", function () {",
									"    pm.response.to.have.status(200);",
									"});"
								],
								"type": "text/javascript"
							}
						}
					],
					"request": {
						"method": "GET",
						"header": [],
						"url": {
							"raw": "{{base_url}}/api/pendrives",
							"host": [
								"{{base_url}}"
							],
							"path": [
								"api",
								"pendrives"
							]
						},
						"description": "This is a GET request and it is used to \"get\" data from an endpoint. There is no request body for a GET request, but you can use query parameters to help specify the resource you want data on (e.g., in this request, we have `id=1`).\n\nA successful GET response will have a `200 OK` status, and should include some kind of response body - for example, HTML web content or JSON data."
					},
					"response": []
				},
				{
					"name": "Get Pendrive by Id",
					"event": [
						{
							"listen": "test",
							"script": {
								"exec": [
									"pm.test(\"Status code is 200\", function () {",
									"    pm.response.to.have.status(200);",
									"});"
								],
								"type": "text/javascript"
							}
						}
					],
					"request": {
						"method": "GET",
						"header": [],
						"url": {
							"raw": "{{base_url}}/api/pendrives/1",
							"host": [
								"{{base_url}}"
							],
							"path": [
								"api",
								"pendrives",
								"1"
							]
						},
						"description": "This is a GET request and it is used to \"get\" data from an endpoint. There is no request body for a GET request, but you can use query parameters to help specify the resource you want data on (e.g., in this request, we have `id=1`).\n\nA successful GET response will have a `200 OK` status, and should include some kind of response body - for example, HTML web content or JSON data."
					},
					"response": []
				},
				{
					"name": "Post Pendrive",
					"event": [
						{
							"listen": "test",
							"script": {
								"exec": [
									"pm.test(\"Successful POST request\", function () {",
									"    pm.expect(pm.response.code).to.be.oneOf([200, 201]);",
									"});",
									""
								],
								"type": "text/javascript"
							}
						}
					],
					"request": {
						"method": "POST",
						"header": [],
						"body": {
							"mode": "raw",
							"raw": "{\n    \"description\": \"Pendrive 5\"\n}",
							"options": {
								"raw": {
									"language": "json"
								}
							}
						},
						"url": {
							"raw": "{{base_url}}/api/pendrives",
							"host": [
								"{{base_url}}"
							],
							"path": [
								"api",
								"pendrives"
							]
						},
						"description": "This is a POST request, submitting data to an API via the request body. This request submits JSON data, and the data is reflected in the response.\n\nA successful POST request typically returns a `200 OK` or `201 Created` response code."
					},
					"response": []
				},
				{
					"name": "Update Pendrive by Id",
					"event": [
						{
							"listen": "test",
							"script": {
								"exec": [
									"pm.test(\"Successful PUT request\", function () {",
									"    pm.expect(pm.response.code).to.be.oneOf([200, 201, 204]);",
									"});",
									""
								],
								"type": "text/javascript"
							}
						}
					],
					"request": {
						"method": "PUT",
						"header": [],
						"body": {
							"mode": "raw",
							"raw": "{\n    \"pendriveStatusId\": 3\n}",
							"options": {
								"raw": {
									"language": "json"
								}
							}
						},
						"url": {
							"raw": "{{base_url}}/api/pendrives/1",
							"host": [
								"{{base_url}}"
							],
							"path": [
								"api",
								"pendrives",
								"1"
							]
						},
						"description": "This is a PUT request and it is used to overwrite an existing piece of data. For instance, after you create an entity with a POST request, you may want to modify that later. You can do that using a PUT request. You typically identify the entity being updated by including an identifier in the URL (eg. `id=1`).\n\nA successful PUT request typically returns a `200 OK`, `201 Created`, or `204 No Content` response code."
					},
					"response": []
				},
				{
					"name": "Delete All Pendrive",
					"event": [
						{
							"listen": "test",
							"script": {
								"exec": [
									"pm.test(\"Successful DELETE request\", function () {",
									"    pm.expect(pm.response.code).to.be.oneOf([200, 202, 204]);",
									"});",
									""
								],
								"type": "text/javascript"
							}
						}
					],
					"request": {
						"method": "DELETE",
						"header": [],
						"body": {
							"mode": "raw",
							"raw": "",
							"options": {
								"raw": {
									"language": "json"
								}
							}
						},
						"url": {
							"raw": "{{base_url}}/api/pendrives",
							"host": [
								"{{base_url}}"
							],
							"path": [
								"api",
								"pendrives"
							]
						},
						"description": "This is a DELETE request, and it is used to delete data that was previously created via a POST request. You typically identify the entity being updated by including an identifier in the URL (eg. `id=1`).\n\nA successful DELETE request typically returns a `200 OK`, `202 Accepted`, or `204 No Content` response code."
					},
					"response": []
				},
				{
					"name": "Delete Pendrive by Id",
					"event": [
						{
							"listen": "test",
							"script": {
								"exec": [
									"pm.test(\"Successful DELETE request\", function () {",
									"    pm.expect(pm.response.code).to.be.oneOf([200, 202, 204]);",
									"});",
									""
								],
								"type": "text/javascript"
							}
						}
					],
					"request": {
						"method": "DELETE",
						"header": [],
						"body": {
							"mode": "raw",
							"raw": "",
							"options": {
								"raw": {
									"language": "json"
								}
							}
						},
						"url": {
							"raw": "{{base_url}}/api/pendrives/2",
							"host": [
								"{{base_url}}"
							],
							"path": [
								"api",
								"pendrives",
								"2"
							]
						},
						"description": "This is a DELETE request, and it is used to delete data that was previously created via a POST request. You typically identify the entity being updated by including an identifier in the URL (eg. `id=1`).\n\nA successful DELETE request typically returns a `200 OK`, `202 Accepted`, or `204 No Content` response code."
					},
					"response": []
				}
			]
		},
		{
			"name": "Pendrive Status",
			"item": [
				{
					"name": "Get All Pendrive Status",
					"event": [
						{
							"listen": "test",
							"script": {
								"exec": [
									"pm.test(\"Status code is 200\", function () {",
									"    pm.response.to.have.status(200);",
									"});"
								],
								"type": "text/javascript"
							}
						}
					],
					"request": {
						"method": "GET",
						"header": [],
						"url": {
							"raw": "{{base_url}}/api/pendriveStatuses",
							"host": [
								"{{base_url}}"
							],
							"path": [
								"api",
								"pendriveStatuses"
							]
						},
						"description": "This is a GET request and it is used to \"get\" data from an endpoint. There is no request body for a GET request, but you can use query parameters to help specify the resource you want data on (e.g., in this request, we have `id=1`).\n\nA successful GET response will have a `200 OK` status, and should include some kind of response body - for example, HTML web content or JSON data."
					},
					"response": []
				},
				{
					"name": "Get Pendrive Status by Id",
					"event": [
						{
							"listen": "test",
							"script": {
								"exec": [
									"pm.test(\"Status code is 200\", function () {",
									"    pm.response.to.have.status(200);",
									"});"
								],
								"type": "text/javascript"
							}
						}
					],
					"request": {
						"method": "GET",
						"header": [],
						"url": {
							"raw": "{{base_url}}/api/pendriveStatuses/3",
							"host": [
								"{{base_url}}"
							],
							"path": [
								"api",
								"pendriveStatuses",
								"3"
							]
						},
						"description": "This is a GET request and it is used to \"get\" data from an endpoint. There is no request body for a GET request, but you can use query parameters to help specify the resource you want data on (e.g., in this request, we have `id=1`).\n\nA successful GET response will have a `200 OK` status, and should include some kind of response body - for example, HTML web content or JSON data."
					},
					"response": []
				},
				{
					"name": "Post Pendrive Status",
					"event": [
						{
							"listen": "test",
							"script": {
								"exec": [
									"pm.test(\"Successful POST request\", function () {",
									"    pm.expect(pm.response.code).to.be.oneOf([200, 201]);",
									"});",
									""
								],
								"type": "text/javascript"
							}
						}
					],
					"request": {
						"method": "POST",
						"header": [],
						"body": {
							"mode": "raw",
							"raw": "{\n    \"description\": \"Lost\"\n}",
							"options": {
								"raw": {
									"language": "json"
								}
							}
						},
						"url": {
							"raw": "{{base_url}}/api/pendriveStatuses",
							"host": [
								"{{base_url}}"
							],
							"path": [
								"api",
								"pendriveStatuses"
							]
						},
						"description": "This is a POST request, submitting data to an API via the request body. This request submits JSON data, and the data is reflected in the response.\n\nA successful POST request typically returns a `200 OK` or `201 Created` response code."
					},
					"response": []
				},
				{
					"name": "Update Pendrive Status by Id",
					"event": [
						{
							"listen": "test",
							"script": {
								"exec": [
									"pm.test(\"Successful PUT request\", function () {",
									"    pm.expect(pm.response.code).to.be.oneOf([200, 201, 204]);",
									"});",
									""
								],
								"type": "text/javascript"
							}
						}
					],
					"request": {
						"method": "PUT",
						"header": [],
						"body": {
							"mode": "raw",
							"raw": "{\n    \"description\": \"Prepared\"\n}",
							"options": {
								"raw": {
									"language": "json"
								}
							}
						},
						"url": {
							"raw": "{{base_url}}/api/pendriveStatuses/3",
							"host": [
								"{{base_url}}"
							],
							"path": [
								"api",
								"pendriveStatuses",
								"3"
							]
						},
						"description": "This is a PUT request and it is used to overwrite an existing piece of data. For instance, after you create an entity with a POST request, you may want to modify that later. You can do that using a PUT request. You typically identify the entity being updated by including an identifier in the URL (eg. `id=1`).\n\nA successful PUT request typically returns a `200 OK`, `201 Created`, or `204 No Content` response code."
					},
					"response": []
				},
				{
					"name": "Delete All Pendrive Status",
					"event": [
						{
							"listen": "test",
							"script": {
								"exec": [
									"pm.test(\"Successful DELETE request\", function () {",
									"    pm.expect(pm.response.code).to.be.oneOf([200, 202, 204]);",
									"});",
									""
								],
								"type": "text/javascript"
							}
						}
					],
					"request": {
						"method": "DELETE",
						"header": [],
						"body": {
							"mode": "raw",
							"raw": "",
							"options": {
								"raw": {
									"language": "json"
								}
							}
						},
						"url": {
							"raw": "{{base_url}}/api/pendriveStatuses",
							"host": [
								"{{base_url}}"
							],
							"path": [
								"api",
								"pendriveStatuses"
							]
						},
						"description": "This is a DELETE request, and it is used to delete data that was previously created via a POST request. You typically identify the entity being updated by including an identifier in the URL (eg. `id=1`).\n\nA successful DELETE request typically returns a `200 OK`, `202 Accepted`, or `204 No Content` response code."
					},
					"response": []
				},
				{
					"name": "Delete Pendrive Status by Id",
					"event": [
						{
							"listen": "test",
							"script": {
								"exec": [
									"pm.test(\"Successful DELETE request\", function () {",
									"    pm.expect(pm.response.code).to.be.oneOf([200, 202, 204]);",
									"});",
									""
								],
								"type": "text/javascript"
							}
						}
					],
					"request": {
						"method": "DELETE",
						"header": [],
						"body": {
							"mode": "raw",
							"raw": "",
							"options": {
								"raw": {
									"language": "json"
								}
							}
						},
						"url": {
							"raw": "{{base_url}}/api/pendriveStatuses/3",
							"host": [
								"{{base_url}}"
							],
							"path": [
								"api",
								"pendriveStatuses",
								"3"
							]
						},
						"description": "This is a DELETE request, and it is used to delete data that was previously created via a POST request. You typically identify the entity being updated by including an identifier in the URL (eg. `id=1`).\n\nA successful DELETE request typically returns a `200 OK`, `202 Accepted`, or `204 No Content` response code."
					},
					"response": []
				}
			]
		},
		{
			"name": "Request Status",
			"item": [
				{
					"name": "Get All Request Status",
					"event": [
						{
							"listen": "test",
							"script": {
								"exec": [
									"pm.test(\"Status code is 200\", function () {",
									"    pm.response.to.have.status(200);",
									"});"
								],
								"type": "text/javascript"
							}
						}
					],
					"request": {
						"method": "GET",
						"header": [],
						"url": {
							"raw": "{{base_url}}/api/requestStatuses",
							"host": [
								"{{base_url}}"
							],
							"path": [
								"api",
								"requestStatuses"
							]
						},
						"description": "This is a GET request and it is used to \"get\" data from an endpoint. There is no request body for a GET request, but you can use query parameters to help specify the resource you want data on (e.g., in this request, we have `id=1`).\n\nA successful GET response will have a `200 OK` status, and should include some kind of response body - for example, HTML web content or JSON data."
					},
					"response": []
				},
				{
					"name": "Get Request Status by Id",
					"event": [
						{
							"listen": "test",
							"script": {
								"exec": [
									"pm.test(\"Status code is 200\", function () {",
									"    pm.response.to.have.status(200);",
									"});"
								],
								"type": "text/javascript"
							}
						}
					],
					"request": {
						"method": "GET",
						"header": [],
						"url": {
							"raw": "{{base_url}}/api/requestStatuses/3",
							"host": [
								"{{base_url}}"
							],
							"path": [
								"api",
								"requestStatuses",
								"3"
							]
						},
						"description": "This is a GET request and it is used to \"get\" data from an endpoint. There is no request body for a GET request, but you can use query parameters to help specify the resource you want data on (e.g., in this request, we have `id=1`).\n\nA successful GET response will have a `200 OK` status, and should include some kind of response body - for example, HTML web content or JSON data."
					},
					"response": []
				},
				{
					"name": "Post Request Status",
					"event": [
						{
							"listen": "test",
							"script": {
								"exec": [
									"pm.test(\"Successful POST request\", function () {",
									"    pm.expect(pm.response.code).to.be.oneOf([200, 201]);",
									"});",
									""
								],
								"type": "text/javascript"
							}
						}
					],
					"request": {
						"method": "POST",
						"header": [],
						"body": {
							"mode": "raw",
							"raw": "{\n    \"description\": \"Cancelled\"\n}",
							"options": {
								"raw": {
									"language": "json"
								}
							}
						},
						"url": {
							"raw": "{{base_url}}/api/requestStatuses",
							"host": [
								"{{base_url}}"
							],
							"path": [
								"api",
								"requestStatuses"
							]
						},
						"description": "This is a POST request, submitting data to an API via the request body. This request submits JSON data, and the data is reflected in the response.\n\nA successful POST request typically returns a `200 OK` or `201 Created` response code."
					},
					"response": []
				},
				{
					"name": "Update Request Status by Id",
					"event": [
						{
							"listen": "test",
							"script": {
								"exec": [
									"pm.test(\"Successful PUT request\", function () {",
									"    pm.expect(pm.response.code).to.be.oneOf([200, 201, 204]);",
									"});",
									""
								],
								"type": "text/javascript"
							}
						}
					],
					"request": {
						"method": "PUT",
						"header": [],
						"body": {
							"mode": "raw",
							"raw": "{\n    \"description\": \"Prepared\"\n}",
							"options": {
								"raw": {
									"language": "json"
								}
							}
						},
						"url": {
							"raw": "{{base_url}}/api/requestStatuses/3",
							"host": [
								"{{base_url}}"
							],
							"path": [
								"api",
								"requestStatuses",
								"3"
							]
						},
						"description": "This is a PUT request and it is used to overwrite an existing piece of data. For instance, after you create an entity with a POST request, you may want to modify that later. You can do that using a PUT request. You typically identify the entity being updated by including an identifier in the URL (eg. `id=1`).\n\nA successful PUT request typically returns a `200 OK`, `201 Created`, or `204 No Content` response code."
					},
					"response": []
				},
				{
					"name": "Delete All Request Status",
					"event": [
						{
							"listen": "test",
							"script": {
								"exec": [
									"pm.test(\"Successful DELETE request\", function () {",
									"    pm.expect(pm.response.code).to.be.oneOf([200, 202, 204]);",
									"});",
									""
								],
								"type": "text/javascript"
							}
						}
					],
					"request": {
						"method": "DELETE",
						"header": [],
						"body": {
							"mode": "raw",
							"raw": "",
							"options": {
								"raw": {
									"language": "json"
								}
							}
						},
						"url": {
							"raw": "{{base_url}}/api/requestStatuses",
							"host": [
								"{{base_url}}"
							],
							"path": [
								"api",
								"requestStatuses"
							]
						},
						"description": "This is a DELETE request, and it is used to delete data that was previously created via a POST request. You typically identify the entity being updated by including an identifier in the URL (eg. `id=1`).\n\nA successful DELETE request typically returns a `200 OK`, `202 Accepted`, or `204 No Content` response code."
					},
					"response": []
				},
				{
					"name": "Delete Request Status by Id",
					"event": [
						{
							"listen": "test",
							"script": {
								"exec": [
									"pm.test(\"Successful DELETE request\", function () {",
									"    pm.expect(pm.response.code).to.be.oneOf([200, 202, 204]);",
									"});",
									""
								],
								"type": "text/javascript"
							}
						}
					],
					"request": {
						"method": "DELETE",
						"header": [],
						"body": {
							"mode": "raw",
							"raw": "",
							"options": {
								"raw": {
									"language": "json"
								}
							}
						},
						"url": {
							"raw": "{{base_url}}/api/requestStatuses/3",
							"host": [
								"{{base_url}}"
							],
							"path": [
								"api",
								"requestStatuses",
								"3"
							]
						},
						"description": "This is a DELETE request, and it is used to delete data that was previously created via a POST request. You typically identify the entity being updated by including an identifier in the URL (eg. `id=1`).\n\nA successful DELETE request typically returns a `200 OK`, `202 Accepted`, or `204 No Content` response code."
					},
					"response": []
				}
			]
		},
		{
			"name": "User",
			"item": [
				{
					"name": "Get All User",
					"event": [
						{
							"listen": "test",
							"script": {
								"exec": [
									"pm.test(\"Status code is 200\", function () {",
									"    pm.response.to.have.status(200);",
									"});"
								],
								"type": "text/javascript"
							}
						}
					],
					"request": {
						"method": "GET",
						"header": [],
						"url": {
							"raw": "{{base_url}}/api/users?email=user2@gmail.com",
							"host": [
								"{{base_url}}"
							],
							"path": [
								"api",
								"users"
							],
							"query": [
								{
									"key": "email",
									"value": "user2@gmail.com"
								}
							]
						},
						"description": "This is a GET request and it is used to \"get\" data from an endpoint. There is no request body for a GET request, but you can use query parameters to help specify the resource you want data on (e.g., in this request, we have `id=1`).\n\nA successful GET response will have a `200 OK` status, and should include some kind of response body - for example, HTML web content or JSON data."
					},
					"response": []
				},
				{
					"name": "Get User by Id",
					"event": [
						{
							"listen": "test",
							"script": {
								"exec": [
									"pm.test(\"Status code is 200\", function () {",
									"    pm.response.to.have.status(200);",
									"});"
								],
								"type": "text/javascript"
							}
						}
					],
					"request": {
						"method": "GET",
						"header": [],
						"url": {
							"raw": "{{base_url}}/api/users/f489fdb3-24c4-413d-a04a-8ab3c1b1e415",
							"host": [
								"{{base_url}}"
							],
							"path": [
								"api",
								"users",
								"f489fdb3-24c4-413d-a04a-8ab3c1b1e415"
							]
						},
						"description": "This is a GET request and it is used to \"get\" data from an endpoint. There is no request body for a GET request, but you can use query parameters to help specify the resource you want data on (e.g., in this request, we have `id=1`).\n\nA successful GET response will have a `200 OK` status, and should include some kind of response body - for example, HTML web content or JSON data."
					},
					"response": []
				},
				{
					"name": "Sign Up",
					"event": [
						{
							"listen": "test",
							"script": {
								"exec": [
									"pm.test(\"Successful POST request\", function () {",
									"    pm.expect(pm.response.code).to.be.oneOf([200, 201]);",
									"});",
									""
								],
								"type": "text/javascript"
							}
						}
					],
					"request": {
						"method": "POST",
						"header": [],
						"body": {
							"mode": "raw",
							"raw": "{\n    \"name\": \"user2\",\n    \"email\": \"user2@gmail.com\",\n    \"password\": \"12345678\"\n}",
							"options": {
								"raw": {
									"language": "json"
								}
							}
						},
						"url": {
							"raw": "{{base_url}}/api/users/signup",
							"host": [
								"{{base_url}}"
							],
							"path": [
								"api",
								"users",
								"signup"
							]
						},
						"description": "This is a POST request, submitting data to an API via the request body. This request submits JSON data, and the data is reflected in the response.\n\nA successful POST request typically returns a `200 OK` or `201 Created` response code."
					},
					"response": []
				},
				{
					"name": "Sign In",
					"event": [
						{
							"listen": "test",
							"script": {
								"exec": [
									"pm.test(\"Successful POST request\", function () {",
									"    pm.expect(pm.response.code).to.be.oneOf([200, 201]);",
									"});",
									""
								],
								"type": "text/javascript"
							}
						}
					],
					"request": {
						"method": "POST",
						"header": [],
						"body": {
							"mode": "raw",
							"raw": "{\n    \"email\": \"user2@gmail.com\",\n    \"password\": \"12345678\"\n}",
							"options": {
								"raw": {
									"language": "json"
								}
							}
						},
						"url": {
							"raw": "{{base_url}}/api/users/sigin",
							"host": [
								"{{base_url}}"
							],
							"path": [
								"api",
								"users",
								"sigin"
							]
						},
						"description": "This is a POST request, submitting data to an API via the request body. This request submits JSON data, and the data is reflected in the response.\n\nA successful POST request typically returns a `200 OK` or `201 Created` response code."
					},
					"response": []
				},
				{
					"name": "Update User by Id",
					"event": [
						{
							"listen": "test",
							"script": {
								"exec": [
									"pm.test(\"Successful PUT request\", function () {",
									"    pm.expect(pm.response.code).to.be.oneOf([200, 201, 204]);",
									"});",
									""
								],
								"type": "text/javascript"
							}
						}
					],
					"request": {
						"method": "PUT",
						"header": [],
						"body": {
							"mode": "raw",
							"raw": "{\n    \"name\": \"user2\",\n    \"email\": \"user2@gmail.com\",\n    \"password\": \"12345678910\"\n}",
							"options": {
								"raw": {
									"language": "json"
								}
							}
						},
						"url": {
							"raw": "{{base_url}}/api/users/ee1fde29-ce2c-4695-ab2c-83e6a6d6c26e",
							"host": [
								"{{base_url}}"
							],
							"path": [
								"api",
								"users",
								"ee1fde29-ce2c-4695-ab2c-83e6a6d6c26e"
							]
						},
						"description": "This is a PUT request and it is used to overwrite an existing piece of data. For instance, after you create an entity with a POST request, you may want to modify that later. You can do that using a PUT request. You typically identify the entity being updated by including an identifier in the URL (eg. `id=1`).\n\nA successful PUT request typically returns a `200 OK`, `201 Created`, or `204 No Content` response code."
					},
					"response": []
				},
				{
					"name": "Delete All Users",
					"event": [
						{
							"listen": "test",
							"script": {
								"exec": [
									"pm.test(\"Successful DELETE request\", function () {",
									"    pm.expect(pm.response.code).to.be.oneOf([200, 202, 204]);",
									"});",
									""
								],
								"type": "text/javascript"
							}
						}
					],
					"request": {
						"method": "DELETE",
						"header": [],
						"body": {
							"mode": "raw",
							"raw": "",
							"options": {
								"raw": {
									"language": "json"
								}
							}
						},
						"url": {
							"raw": "{{base_url}}/api/users",
							"host": [
								"{{base_url}}"
							],
							"path": [
								"api",
								"users"
							]
						},
						"description": "This is a DELETE request, and it is used to delete data that was previously created via a POST request. You typically identify the entity being updated by including an identifier in the URL (eg. `id=1`).\n\nA successful DELETE request typically returns a `200 OK`, `202 Accepted`, or `204 No Content` response code."
					},
					"response": []
				},
				{
					"name": "Delete User by Id",
					"event": [
						{
							"listen": "test",
							"script": {
								"exec": [
									"pm.test(\"Successful DELETE request\", function () {",
									"    pm.expect(pm.response.code).to.be.oneOf([200, 202, 204]);",
									"});",
									""
								],
								"type": "text/javascript"
							}
						}
					],
					"request": {
						"method": "DELETE",
						"header": [],
						"body": {
							"mode": "raw",
							"raw": "",
							"options": {
								"raw": {
									"language": "json"
								}
							}
						},
						"url": {
							"raw": "{{base_url}}/api/users/94700622-0178-4c61-801b-61644ab5ecfe",
							"host": [
								"{{base_url}}"
							],
							"path": [
								"api",
								"users",
								"94700622-0178-4c61-801b-61644ab5ecfe"
							]
						},
						"description": "This is a DELETE request, and it is used to delete data that was previously created via a POST request. You typically identify the entity being updated by including an identifier in the URL (eg. `id=1`).\n\nA successful DELETE request typically returns a `200 OK`, `202 Accepted`, or `204 No Content` response code."
					},
					"response": []
				}
			]
		}
	]
}